slater.py
slater-0.0.0.dist-info/LICENSE
slater-0.0.0.dist-info/METADATA
slater-0.0.0.dist-info/WHEEL
slater-0.0.0.dist-info/top_level.txt
slater-0.0.0.dist-info/RECORD
