Metadata-Version: 2.1
Name: slater
Version: 0.0.0
Summary: A module for manipulating Slater determinants.
Home-page: https://github.com/kimt33/slater
Author: Taewon D. Kim
Author-email: david.kim.91@gmail.com
License: UNKNOWN
Project-URL: Bug Reports, https://github.com/kimt33/slater/issues
Project-URL: Organization, https://github.com/quantumelephant/
Project-URL: Source, https://github.com/kimt33/slater/
Keywords: quantum chemistry Slater determinant
Platform: UNKNOWN
Classifier: Development Status :: 1 - Planning
Classifier: Intended Audience :: Science/Research
Classifier: Intended Audience :: Education
Classifier: Topic :: Scientific/Engineering :: Chemistry
Classifier: License :: OSI Approved :: GNU Lesser General Public License v3 (LGPLv3)
Classifier: Programming Language :: Python :: 2.7
Classifier: Programming Language :: Python :: 3.0
Classifier: Programming Language :: Python :: 3.1
Classifier: Programming Language :: Python :: 3.2
Classifier: Programming Language :: Python :: 3.3
Classifier: Programming Language :: Python :: 3.4
Classifier: Programming Language :: Python :: 3.5
Classifier: Programming Language :: Python :: 3.6
Classifier: Programming Language :: Python :: 3.7
Requires-Python: >=2.7
Requires-Dist: gmpy2
Provides-Extra: test
Requires-Dist: pytest ; extra == 'test'
Requires-Dist: pytest-cov ; extra == 'test'
